./.dockerignore
./.gitignore
./Dockerfile
./LICENSE
./PKG-INFO
./README.md
./mcp_server.py
./pyproject.toml
./requirements.txt
./run_local.bat
./run_local.ps1
./run_local.sh
iflow_mcp_mcp_searxng_enhanced-0.1.0.dist-info/METADATA
iflow_mcp_mcp_searxng_enhanced-0.1.0.dist-info/WHEEL
iflow_mcp_mcp_searxng_enhanced-0.1.0.dist-info/entry_points.txt
iflow_mcp_mcp_searxng_enhanced-0.1.0.dist-info/licenses/LICENSE
iflow_mcp_mcp_searxng_enhanced-0.1.0.dist-info/RECORD
