Metadata-Version: 2.4
Name: iflow-mcp_mcp-searxng-enhanced
Version: 0.1.0
Summary: A Model Context Protocol (MCP) server for category-aware web search, website scraping, and date/time tools
Project-URL: Homepage, https://github.com/OvertliDS/mcp-searxng-enhanced
Project-URL: Repository, https://github.com/iflow-mcp/mcp-searxng-enhanced
Project-URL: Issues, https://github.com/OvertliDS/mcp-searxng-enhanced/issues
Author: OvertliDS
License: MIT
License-File: LICENSE
Classifier: Development Status :: 3 - Alpha
Classifier: Intended Audience :: Developers
Classifier: License :: OSI Approved :: MIT License
Classifier: Programming Language :: Python :: 3
Classifier: Programming Language :: Python :: 3.9
Classifier: Programming Language :: Python :: 3.10
Classifier: Programming Language :: Python :: 3.11
Classifier: Programming Language :: Python :: 3.12
Requires-Python: >=3.9
Requires-Dist: beautifulsoup4<5.0.0,>=4.9.0
Requires-Dist: cachetools<6.0.0,>=5.0.0
Requires-Dist: filetype<2.0.0,>=1.1.0
Requires-Dist: httpx<1.0.0,>=0.20.0
Requires-Dist: pydantic<3.0.0,>=1.8.0
Requires-Dist: pymupdf4llm<0.1,>=0.0.20
Requires-Dist: pymupdf<2.0.0,>=1.20.0
Requires-Dist: python-dateutil<3.0.0,>=2.8.0
Requires-Dist: trafilatura<2.0.0,>=1.8.0
Requires-Dist: tzdata>=2022.1
